llvm_lnt-0.4.2.dev0.dist-info/licenses/LICENSE.TXT
lnt/__init__.py
lnt/external/__init__.py
lnt/external/stats/README.txt
lnt/external/stats/__init__.py
lnt/external/stats/pstat.py
lnt/external/stats/stats.py
lnt/formats/JSONFormat.py
lnt/formats/PlistFormat.py
lnt/formats/__init__.py
lnt/lnttool/__init__.py
lnt/lnttool/admin.py
lnt/lnttool/common.py
lnt/lnttool/convert.py
lnt/lnttool/create.py
lnt/lnttool/import_data.py
lnt/lnttool/import_report.py
lnt/lnttool/main.py
lnt/lnttool/updatedb.py
lnt/lnttool/viewcomparison.py
lnt/server/__init__.py
lnt/server/config.py
lnt/server/instance.py
lnt/server/db/__init__.py
lnt/server/db/fieldchange.py
lnt/server/db/migrate.py
lnt/server/db/regression.py
lnt/server/db/rules_manager.py
lnt/server/db/search.py
lnt/server/db/testsuite.py
lnt/server/db/testsuitedb.py
lnt/server/db/util.py
lnt/server/db/v4db.py
lnt/server/db/migrations/README.txt
lnt/server/db/migrations/__init__.py
lnt/server/db/migrations/new_suite.py
lnt/server/db/migrations/upgrade_0_to_1.py
lnt/server/db/migrations/upgrade_10_to_11.py
lnt/server/db/migrations/upgrade_11_to_12.py
lnt/server/db/migrations/upgrade_12_to_13.py
lnt/server/db/migrations/upgrade_13_to_14.py
lnt/server/db/migrations/upgrade_14_to_15.py
lnt/server/db/migrations/upgrade_15_to_16.py
lnt/server/db/migrations/upgrade_16_to_17.py
lnt/server/db/migrations/upgrade_1_to_2.py
lnt/server/db/migrations/upgrade_2_to_3.py
lnt/server/db/migrations/upgrade_3_to_4.py
lnt/server/db/migrations/upgrade_4_to_5.py
lnt/server/db/migrations/upgrade_5_to_6.py
lnt/server/db/migrations/upgrade_6_to_7.py
lnt/server/db/migrations/upgrade_7_to_8.py
lnt/server/db/migrations/upgrade_8_to_9.py
lnt/server/db/migrations/upgrade_9_to_10.py
lnt/server/db/migrations/util.py
lnt/server/db/migrations/__pycache__/__init__.cpython-310.pyc
lnt/server/db/migrations/__pycache__/upgrade_0_to_1.cpython-310.pyc
lnt/server/db/migrations/__pycache__/upgrade_2_to_3.cpython-310.pyc
lnt/server/db/migrations/__pycache__/upgrade_7_to_8.cpython-310.pyc
llvm_lnt-0.4.2.dev0.dist-info/METADATA
llvm_lnt-0.4.2.dev0.dist-info/WHEEL
llvm_lnt-0.4.2.dev0.dist-info/entry_points.txt
llvm_lnt-0.4.2.dev0.dist-info/top_level.txt
llvm_lnt-0.4.2.dev0.dist-info/RECORD
